annotations/__init__.py
annotations/apps.py
annotations/models.py
annotations/tests.py
annotations/urls.py
annotations/migrations/0001_initial.py
annotations/migrations/__init__.py
jama/__init__.py
jama/__main__.py
jama/apps.py
jama/asgi.py
jama/settings.py
jama/urls.py
jama/views.py
jama/wsgi.py
jama/management/commands/printconf.py
jama/management/commands/repl.py
jama/templates/common.html
jama/templates/docs.html
jama/templates/homepage.html
oai/__init__.py
oai/apps.py
oai/models.py
oai/tests.py
oai/urls.py
oai/views.py
oai/migrations/__init__.py
oai/templates/oai/errors.xml
oai/templates/oai/get_record.xml
oai/templates/oai/identify.xml
oai/templates/oai/list_identifiers.xml
oai/templates/oai/list_metadata_formats.xml
oai/templates/oai/list_records.xml
oai/templates/oai/list_sets.xml
resources/__init__.py
resources/apps.py
resources/helpers.py
resources/models.py
resources/tasks.py
resources/urls.py
resources/views.py
resources/management/commands/addlocalfiles.py
resources/management/commands/cleanpartialuploads.py
resources/management/commands/denormsizes.py
resources/management/commands/ensureiiif.py
resources/management/commands/exportproject.py
resources/management/commands/fusefs.py
resources/management/commands/jamagiveaccess.py
resources/management/commands/loadfixtures.py
resources/management/commands/makesymlinks.py
resources/management/commands/mimes.json
resources/management/commands/newjamaproject.py
resources/management/commands/property.csv
resources/management/commands/resource_class.csv
resources/management/commands/retile.py
resources/management/commands/vocabulary.csv
resources/migrations/0001_initial.py
resources/migrations/0002_auto_20201125_1111.py
resources/migrations/0003_resource_ptr_owner.py
resources/migrations/0004_auto_20210128_1046.py
resources/migrations/0005_descendants_count.py
resources/migrations/0006_collection_public_access.py
resources/migrations/0007_auto_20210225_1329.py
resources/migrations/0008_metadata_expose.py
jama_certic-0.1.0.dist-info/METADATA
jama_certic-0.1.0.dist-info/WHEEL
jama_certic-0.1.0.dist-info/entry_points.txt
jama_certic-0.1.0.dist-info/licenses/LICENSE.txt
jama_certic-0.1.0.dist-info/RECORD
