Metadata-Version: 2.4
Name: jama-CERTIC
Version: 0.1.0
Summary: APIs et interfaces de stockage de médias.
Project-URL: Repository, https://git.unicaen.fr/certic/jama
Author-email: Mickaël Desfrênes <mickael.desfrenes@unicaen.fr>
Maintainer-email: Mickaël Desfrênes <mickael.desfrenes@unicaen.fr>
License-Expression: CECILL-B
License-File: LICENSE.txt
Requires-Python: <4.0,>=3.12
Requires-Dist: ark-client-certic>=0.2.0
Requires-Dist: bpython>=0.25
Requires-Dist: deskew>=1.3.3
Requires-Dist: django-auth-cli-certic>=0.1.5
Requires-Dist: django-cachalot>=2.7.0
Requires-Dist: django-cors-headers>=4.7.0
Requires-Dist: django-extensions>=3.1.5
Requires-Dist: django-modshib-certic>=0.2.2
Requires-Dist: django-ranged-fileresponse>=0.1.2
Requires-Dist: django-vite>=2.1.3
Requires-Dist: django-webpack-loader>=3.1.0
Requires-Dist: django>=5.1.0
Requires-Dist: fusepy>=3.0.1
Requires-Dist: gunicorn>=23.0.0
Requires-Dist: huey>=2.5.3
Requires-Dist: jama-client-certic>=0.0.24
Requires-Dist: markdown2>=2.4.3
Requires-Dist: numpy>=2.1.3
Requires-Dist: opencv-python-headless>=4.6.0
Requires-Dist: openpyxl>=3.1.2
Requires-Dist: pick>=2.4.0
Requires-Dist: psycopg2-binary>=2.9.10
Requires-Dist: pydotplus>=2.0.2
Requires-Dist: pyexiftool>=0.5.3
Requires-Dist: pytesseract>=0.3.10
Requires-Dist: python-dotenv>=1.0.0
Requires-Dist: pyvips>=2.2.1
Requires-Dist: rich>=14.0.0
Requires-Dist: unidecode>=1.3.4
